simple_math/__init__.py
simple_math/operations.py
test_simple_math-1.1.0.dist-info/licenses/LICENSE
test_simple_math-1.1.0.dist-info/METADATA
test_simple_math-1.1.0.dist-info/WHEEL
test_simple_math-1.1.0.dist-info/top_level.txt
test_simple_math-1.1.0.dist-info/RECORD
